chainsaw/__init__.py
chainsaw/chainsaw.py
git_chainsaw-0.1.11.dist-info/METADATA
git_chainsaw-0.1.11.dist-info/WHEEL
git_chainsaw-0.1.11.dist-info/entry_points.txt
git_chainsaw-0.1.11.dist-info/top_level.txt
git_chainsaw-0.1.11.dist-info/RECORD
