Metadata-Version: 2.1
Name: git-chainsaw
Version: 0.1.11
Summary: A lightweight wrapper around git subtrees that lets you work with many subtrees at once
Home-page: https://github.com/JakeHillHub/port-linker
Author: Jake Hill
Author-email: jakehillgithub@gmail.net
License: UNKNOWN
Keywords: subtree
Platform: UNKNOWN
Classifier: Development Status :: 4 - Beta
Classifier: Intended Audience :: Developers
